physical_education/__init__.py
physical_education/__main__.py
physical_education/analysis.py
physical_education/base.py
physical_education/collocation.py
physical_education/constrain.py
physical_education/damper.py
physical_education/drag.py
physical_education/foot.py
physical_education/init_tools.py
physical_education/links.py
physical_education/meta.py
physical_education/motor.py
physical_education/node.py
physical_education/spring.py
physical_education/symdef.py
physical_education/system.py
physical_education/utils.py
physical_education/variable_list.py
physical_education/visual.py
physical_education-0.2.0.dist-info/entry_points.txt
physical_education-0.2.0.dist-info/LICENSE
physical_education-0.2.0.dist-info/WHEEL
physical_education-0.2.0.dist-info/METADATA
physical_education-0.2.0.dist-info/RECORD
