Metadata-Version: 2.1
Name: physical_education
Version: 0.2.0
Summary: A library for research into legged critters
Home-page: https://github.com/alknemeyer/physical_education
License: UNKNOWN
Keywords: trajectory optimization,dynamics,robotics,biomechanics
Author: Alexander Knemeyer
Author-email: alknemeyer@hey.com
Requires-Python: >=3.6
Classifier: Intended Audience :: Science/Research
Classifier: License :: OSI Approved :: MIT License
Classifier: Natural Language :: English
Classifier: Programming Language :: Python :: 3.6
Classifier: Programming Language :: Python :: 3.7
Classifier: Programming Language :: Python :: 3.8
Classifier: Programming Language :: Python :: 3.9
Classifier: Programming Language :: Python :: Implementation :: CPython
Classifier: Programming Language :: Python :: Implementation :: PyPy
Classifier: Topic :: Scientific/Engineering
Classifier: Typing :: Typed
Requires-Dist: dill ~= 0.3
Requires-Dist: matplotlib ~= 3.1
Requires-Dist: numpy ~= 1.10
Requires-Dist: pyomo ~= 5.7.1
Requires-Dist: sympy ~= 1.3
Requires-Dist: typing_extensions ~= 3.0
